src/mathtext-fastapi/__init__.py
src/mathtext-fastapi/app.py
src/mathtext-fastapi/sentiment.py
src/mathtext-fastapi/text2int.py
mathtext_fastapi-0.1.3.dist-info/METADATA
mathtext_fastapi-0.1.3.dist-info/WHEEL
mathtext_fastapi-0.1.3.dist-info/RECORD
