Metadata-Version: 2.1
Name: mathtext-fastapi
Version: 0.1.3
Summary: 
Author: Cetin CAKIR
Author-email: cetincakirtr@gmail.com
Requires-Python: >=3.10,<4.0
Classifier: Programming Language :: Python :: 3
Classifier: Programming Language :: Python :: 3.10
Classifier: Programming Language :: Python :: 3.11
